odoo/addons/stock_picking_back2draft/README.rst
odoo/addons/stock_picking_back2draft/__init__.py
odoo/addons/stock_picking_back2draft/__manifest__.py
odoo/addons/stock_picking_back2draft/i18n/ca.po
odoo/addons/stock_picking_back2draft/i18n/de.po
odoo/addons/stock_picking_back2draft/i18n/es.po
odoo/addons/stock_picking_back2draft/i18n/es_AR.po
odoo/addons/stock_picking_back2draft/i18n/es_MX.po
odoo/addons/stock_picking_back2draft/i18n/fi.po
odoo/addons/stock_picking_back2draft/i18n/fr.po
odoo/addons/stock_picking_back2draft/i18n/hr.po
odoo/addons/stock_picking_back2draft/i18n/it.po
odoo/addons/stock_picking_back2draft/i18n/pt.po
odoo/addons/stock_picking_back2draft/i18n/pt_BR.po
odoo/addons/stock_picking_back2draft/i18n/sl.po
odoo/addons/stock_picking_back2draft/i18n/stock_picking_back2draft.pot
odoo/addons/stock_picking_back2draft/i18n/tr.po
odoo/addons/stock_picking_back2draft/i18n/tr_TR.po
odoo/addons/stock_picking_back2draft/i18n/zh_CN.po
odoo/addons/stock_picking_back2draft/models/__init__.py
odoo/addons/stock_picking_back2draft/models/stock_move.py
odoo/addons/stock_picking_back2draft/models/stock_picking.py
odoo/addons/stock_picking_back2draft/readme/CONTRIBUTORS.rst
odoo/addons/stock_picking_back2draft/readme/DESCRIPTION.rst
odoo/addons/stock_picking_back2draft/readme/USAGE.rst
odoo/addons/stock_picking_back2draft/static/description/icon.png
odoo/addons/stock_picking_back2draft/static/description/index.html
odoo/addons/stock_picking_back2draft/tests/__init__.py
odoo/addons/stock_picking_back2draft/tests/test_picking.py
odoo/addons/stock_picking_back2draft/views/picking_view.xml
odoo14_addon_stock_picking_back2draft-14.0.1.0.1.dev11.dist-info/METADATA
odoo14_addon_stock_picking_back2draft-14.0.1.0.1.dev11.dist-info/WHEEL
odoo14_addon_stock_picking_back2draft-14.0.1.0.1.dev11.dist-info/top_level.txt
odoo14_addon_stock_picking_back2draft-14.0.1.0.1.dev11.dist-info/RECORD
